polybar_online/__init__.py
polybar_online/loop.py
polybar_online/main.py
polybar_online/settings.py
polybar_online/status_printer/__init__.py
polybar_online/status_printer/flush_print.py
polybar_online/status_printer/notify.py
polybar_online/status_printer/status_printer.py
polybar_online/utils/__init__.py
polybar_online/utils/check_internet_connection.py
polybar_online/utils/parse_args.py
polybar_online-1.0.0.dist-info/LICENSE.txt
polybar_online-1.0.0.dist-info/METADATA
polybar_online-1.0.0.dist-info/WHEEL
polybar_online-1.0.0.dist-info/entry_points.txt
polybar_online-1.0.0.dist-info/RECORD
