Metadata-Version: 2.1
Name: polybar-online
Version: 1.0.0
Summary: Script for Polybar that checks connection to the Internet
Home-page: https://github.com/Leetovskiy/polybar-online
License: Apache-2.0
Keywords: polybar,tuning
Author: Vitaliy Zaitsev
Author-email: dev.zaitsev@gmail.com
Requires-Python: >=3.10,<4.0
Classifier: Intended Audience :: Other Audience
Classifier: Intended Audience :: System Administrators
Classifier: License :: OSI Approved :: Apache Software License
Classifier: Natural Language :: English
Classifier: Operating System :: POSIX :: Linux
Classifier: Programming Language :: Python :: 3
Classifier: Programming Language :: Python :: 3.10
Classifier: Programming Language :: Python :: 3.11
Classifier: Topic :: Desktop Environment :: Window Managers
Classifier: Topic :: Internet
Project-URL: Repository, https://github.com/Leetovskiy/polybar-online
